CGRtools/preparer.py
CGRtools/__init__.py
CGRtools/exceptions.py
CGRtools/_functions.py
CGRtools/containers/cgr.py
CGRtools/containers/reaction.py
CGRtools/containers/bonds.py
CGRtools/containers/query.py
CGRtools/containers/__init__.py
CGRtools/containers/_unpack.cpython-312-x86_64-linux-gnu.so
CGRtools/containers/cgr_query.py
CGRtools/containers/common.py
CGRtools/containers/molecule.py
CGRtools/containers/_unpack.pyx
CGRtools/utils/grid.py
CGRtools/utils/__init__.py
CGRtools/utils/functional_groups.py
CGRtools/utils/rdkit.py
CGRtools/files/MRVrw.py
CGRtools/files/PDBrw.py
CGRtools/files/SMILESrw.py
CGRtools/files/XYZrw.py
CGRtools/files/__init__.py
CGRtools/files/INCHIrw.py
CGRtools/files/RDFrw.py
CGRtools/files/SDFrw.py
CGRtools/files/_mdl/write.py
CGRtools/files/_mdl/__init__.py
CGRtools/files/_mdl/rw.py
CGRtools/files/_mdl/ewrite.py
CGRtools/files/_mdl/stereo.py
CGRtools/files/_mdl/rxn.py
CGRtools/files/_mdl/erxn.py
CGRtools/files/_mdl/parser.py
CGRtools/files/_mdl/mol.py
CGRtools/files/_mdl/emol.py
CGRtools/reactor/cgr.py
CGRtools/reactor/__init__.py
CGRtools/reactor/base.py
CGRtools/reactor/reactor.py
CGRtools/attributes/query.py
CGRtools/attributes/__init__.py
CGRtools/attributes/molecule.py
CGRtools/periodictable/groupII.py
CGRtools/periodictable/groupXI.py
CGRtools/periodictable/groupXVI.py
CGRtools/periodictable/groupI.py
CGRtools/periodictable/groupXVII.py
CGRtools/periodictable/__init__.py
CGRtools/periodictable/groupIII.py
CGRtools/periodictable/groupVII.py
CGRtools/periodictable/periods.py
CGRtools/periodictable/groupXIII.py
CGRtools/periodictable/groups.py
CGRtools/periodictable/groupV.py
CGRtools/periodictable/groupX.py
CGRtools/periodictable/groupVIII.py
CGRtools/periodictable/groupXVIII.py
CGRtools/periodictable/groupIX.py
CGRtools/periodictable/groupXIV.py
CGRtools/periodictable/groupIV.py
CGRtools/periodictable/groupVI.py
CGRtools/periodictable/groupXV.py
cgrtools_stable-4.2.13.dist-info/WHEEL
cgrtools_stable-4.2.13.dist-info/METADATA
cgrtools_stable-4.2.13.dist-info/top_level.txt
cgrtools_stable-4.2.13.dist-info/RECORD
cgrtools_stable-4.2.13.dist-info/licenses/LICENSE
