Metadata-Version: 2.4
Name: cgrtools-stable
Version: 4.2.13
Summary: Chemical Graph Reaction (CGR) Toolkit — representation, manipulation and analysis of molecules, reactions and reaction mechanisms
Author: Valentina Afonina
Author-email: "Dr. Ramil Nugmanov" <nougmanoff@protonmail.com>, "Dr. Timur Madzhidov" <tmadzhidov@gmail.com>, Tagir Akhmetshin <tagirshin@gmail.com>
License: LGPL-3.0-or-later
Keywords: chemoinformatics,chemistry,CGR,molecule,reaction
Classifier: Environment :: Plugins
Classifier: Intended Audience :: Science/Research
Classifier: License :: OSI Approved :: GNU Lesser General Public License v3 or later (LGPLv3+)
Classifier: Operating System :: OS Independent
Classifier: Programming Language :: Python
Classifier: Programming Language :: Python :: 3 :: Only
Classifier: Programming Language :: Python :: 3.7
Classifier: Programming Language :: Python :: 3.8
Classifier: Programming Language :: Python :: 3.9
Classifier: Programming Language :: Python :: 3.10
Classifier: Topic :: Scientific/Engineering
Classifier: Topic :: Scientific/Engineering :: Chemistry
Classifier: Topic :: Scientific/Engineering :: Information Analysis
Classifier: Topic :: Software Development
Classifier: Topic :: Software Development :: Libraries
Classifier: Topic :: Software Development :: Libraries :: Python Modules
Requires-Python: >=3.8
License-File: LICENSE
Requires-Dist: CachedMethods<0.2,>=0.1.4
Requires-Dist: mini-racer>=0.12.0
Requires-Dist: lxml>=4.1
Requires-Dist: numpy>=1.18
Requires-Dist: numba>=0.50
Dynamic: license-file
